query_farm_sql_manipulation/__init__.py
query_farm_sql_manipulation/test_transforms.py
query_farm_sql_manipulation/transforms.py
query_farm_sql_manipulation-0.1.7.dist-info/METADATA
query_farm_sql_manipulation-0.1.7.dist-info/WHEEL
query_farm_sql_manipulation-0.1.7.dist-info/licenses/LICENSE
query_farm_sql_manipulation-0.1.7.dist-info/RECORD
