Metadata-Version: 2.3
Name: query-farm-sql-manipulation
Version: 0.1.7
Summary: A Python library for intelligent SQL predicate manipulation using SQLGlot. This library provides tools to safely remove specific predicates from `SQL WHERE` clauses and filter SQL statements based on column availability.
Project-URL: Repository, https://github.com/query-farm/python-sql-manipulation.git
Project-URL: Issues, https://github.com/query-farm/python-sql-manipulation/issues
Author-email: Rusty Conover <rusty@query.farm>
Keywords: predicate parsing,predicates,sql,sql parsing
Classifier: Development Status :: 4 - Beta
Classifier: Intended Audience :: Developers
Classifier: Programming Language :: Python :: 3.11
Classifier: Topic :: Database
Classifier: Topic :: Database :: Database Engines/Servers
Requires-Python: >=3.11
Requires-Dist: sqlglot>=26.33.0
